RPiMusic/__init__.py
RPiMusic/rpimusicd.py
RPiMusic-0.0.8.dist-info/METADATA
RPiMusic-0.0.8.dist-info/RECORD
RPiMusic-0.0.8.dist-info/WHEEL
RPiMusic-0.0.8.dist-info/entry_points.txt
RPiMusic-0.0.8.dist-info/top_level.txt
