Metadata-Version: 2.1
Name: RPiMusic
Version: 0.0.8
Summary: Play URLs from AMQP messages via mpv
Home-page: https://github.com/avollmerhaus/RPiMusic
Author: Aljoscha Vollmerhaus
Author-email: pydev@aljoscha.vollmerhaus.net
License: UNKNOWN
Platform: UNKNOWN
Classifier: Programming Language :: Python :: 3
Classifier: License :: OSI Approved :: GNU General Public License v3 (GPLv3)
Classifier: Operating System :: POSIX :: Linux
Classifier: Environment :: Console
Requires-Dist: pika
